bdflib/__init__.py
bdflib/effects.py
bdflib/glyph_combining.py
bdflib/model.py
bdflib/reader.py
bdflib/tools.py
bdflib/writer.py
bdflib/xlfd.py
bdflib/test/__init__.py
bdflib/test/test_effects.py
bdflib/test/test_glyph_combining.py
bdflib/test/test_model.py
bdflib/test/test_reader.py
bdflib/test/test_writer.py
bdflib/test/test_xlfd.py
bdflib-2.0.0.dist-info/COPYING
bdflib-2.0.0.dist-info/METADATA
bdflib-2.0.0.dist-info/WHEEL
bdflib-2.0.0.dist-info/entry_points.txt
bdflib-2.0.0.dist-info/top_level.txt
bdflib-2.0.0.dist-info/RECORD
