Metadata-Version: 2.1
Name: bdflib
Version: 2.0.0
Summary: Library for working with BDF font files.
Home-page: https://gitlab.com/Screwtapello/bdflib/
Author: Timothy Allen
Author-email: screwtape@froup.com
License: UNKNOWN
Platform: UNKNOWN
License-File: COPYING
